aush/__init__.py
aush-0.9.14.dist-info/METADATA
aush-0.9.14.dist-info/WHEEL
aush-0.9.14.dist-info/top_level.txt
aush-0.9.14.dist-info/RECORD
