Metadata-Version: 2.2
Name: aush
Version: 0.9.14
Summary: Pythonic subprocess library
Author-email: Keith Devens <keith@keithdevens.com>
License: MIT License
Project-URL: Repository, https://github.com/kbd/aush
Requires-Python: >=3.10
